<?xml version="1.0" encoding="UTF-8"?><?xml-stylesheet href="http://www.accessdata.fda.gov/spl/stylesheet/spl.xsl" type="text/xsl"?>
<document xmlns="urn:hl7-org:v3" xmlns:xsi="http://www.w3.org/2001/XMLSchema-instance" xsi:schemaLocation="urn:hl7-org:v3 http://www.accessdata.fda.gov/spl/schema/spl.xsd">
   <id root="ddf2a781-8150-4452-97df-a41ff3caeff3"/>
   <code code="34391-3" codeSystem="2.16.840.1.113883.6.1" displayName="HUMAN PRESCRIPTION DRUG LABEL"/>
   <title>These highlights do not include all the information needed to use [Phentermine Hydrochloride Tablets, USP] safely and effectively.  See full prescribing information for [Phentermine Hydrochloride Tablets, USP   CIV for oral use<br/>].<br/>Initial U.S. Approval: [1959]</title>
   <effectiveTime value="20150226"/>
   <setId root="ddf2a781-8150-4452-97df-a41ff3caeff3"/>
   <versionNumber value="2"/>
   <author>
      <time/>
      <assignedEntity>
         <representedOrganization>
            <id extension="078420272" root="1.3.6.1.4.1.519.1"/>
            <name>Mikah Pharma, LLC</name>
            <assignedEntity>
               <assignedOrganization>
                  <id extension="785398728" root="1.3.6.1.4.1.519.1"/>
                  <name>Elite Laboratories, Inc.</name>
                  <assignedEntity>
                     <assignedOrganization>
                        <id extension="785398728" root="1.3.6.1.4.1.519.1"/>
                        <name>Elite Laboratories, Inc.</name>
                     </assignedOrganization>
                     <performance>
                        <actDefinition>
                           <code code="C43360" codeSystem="2.16.840.1.113883.3.26.1.1" displayName="MANUFACTURE"/>
                           <product>
                              <manufacturedProduct classCode="MANU">
                                 <manufacturedMaterialKind>
                                    <code code="61939-810" codeSystem="2.16.840.1.113883.6.69"/>
                                 </manufacturedMaterialKind>
                              </manufacturedProduct>
                           </product>
                        </actDefinition>
                     </performance>
                     <performance>
                        <actDefinition>
                           <code code="C84732" codeSystem="2.16.840.1.113883.3.26.1.1" displayName="LABEL"/>
                           <product>
                              <manufacturedProduct classCode="MANU">
                                 <manufacturedMaterialKind>
                                    <code code="61939-810" codeSystem="2.16.840.1.113883.6.69"/>
                                 </manufacturedMaterialKind>
                              </manufacturedProduct>
                           </product>
                        </actDefinition>
                     </performance>
                  </assignedEntity>
               </assignedOrganization>
            </assignedEntity>
         </representedOrganization>
      </assignedEntity>
   </author>
   <component>
      <structuredBody>
         <component>
            <section>
               <id root="1c207bab-2a68-42b1-a792-430f60889ae6"/>
               <code code="48780-1" codeSystem="2.16.840.1.113883.6.1" displayName="SPL product data elements section"/>
               <effectiveTime value="20150226"/>
               <subject>
                  <manufacturedProduct>
                     <manufacturedProduct>
                        <code code="61939-810" codeSystem="2.16.840.1.113883.6.69"/>
                        <name>Phentermine Hydrochloride</name>
                        <formCode code="C42998" codeSystem="2.16.840.1.113883.3.26.1.1" displayName="TABLET"/>
                        <asEntityWithGeneric>
                           <genericMedicine>
                              <name>Phentermine Hydrochloride</name>
                           </genericMedicine>
                        </asEntityWithGeneric>
                        <ingredient classCode="ACTIB">
                           <quantity>
                              <numerator unit="mg" value="37.5"/>
                              <denominator unit="1" value="1"/>
                           </quantity>
                           <ingredientSubstance>
                              <code code="0K2I505OTV" codeSystem="2.16.840.1.113883.4.9"/>
                              <name>PHENTERMINE HYDROCHLORIDE</name>
                              <activeMoiety>
                                 <activeMoiety>
                                    <code code="C045TQL4WP" codeSystem="2.16.840.1.113883.4.9"/>
                                    <name>PHENTERMINE</name>
                                 </activeMoiety>
                              </activeMoiety>
                           </ingredientSubstance>
                        </ingredient>
                        <ingredient classCode="IACT">
                           <ingredientSubstance>
                              <code code="O8232NY3SJ" codeSystem="2.16.840.1.113883.4.9"/>
                              <name>STARCH, CORN</name>
                           </ingredientSubstance>
                        </ingredient>
                        <ingredient classCode="IACT">
                           <ingredientSubstance>
                              <code code="3SY5LH9PMK" codeSystem="2.16.840.1.113883.4.9"/>
                              <name>ANHYDROUS LACTOSE</name>
                           </ingredientSubstance>
                        </ingredient>
                        <ingredient classCode="IACT">
                           <ingredientSubstance>
                              <code code="70097M6I30" codeSystem="2.16.840.1.113883.4.9"/>
                              <name>MAGNESIUM STEARATE</name>
                           </ingredientSubstance>
                        </ingredient>
                        <ingredient classCode="IACT">
                           <ingredientSubstance>
                              <code code="4ELV7Z65AP" codeSystem="2.16.840.1.113883.4.9"/>
                              <name>STEARIC ACID</name>
                           </ingredientSubstance>
                        </ingredient>
                        <ingredient classCode="IACT">
                           <ingredientSubstance>
                              <code code="ETJ7Z6XBU4" codeSystem="2.16.840.1.113883.4.9"/>
                              <name>SILICON DIOXIDE</name>
                           </ingredientSubstance>
                        </ingredient>
                        <ingredient classCode="IACT">
                           <ingredientSubstance>
                              <code code="OP1R32D61U" codeSystem="2.16.840.1.113883.4.9"/>
                              <name>CELLULOSE, MICROCRYSTALLINE</name>
                           </ingredientSubstance>
                        </ingredient>
                        <ingredient classCode="IACT">
                           <ingredientSubstance>
                              <code code="C151H8M554" codeSystem="2.16.840.1.113883.4.9"/>
                              <name>SUCROSE</name>
                           </ingredientSubstance>
                        </ingredient>
                        <asContent>
                           <quantity>
                              <numerator unit="1" value="100"/>
                              <denominator value="1"/>
                           </quantity>
                           <containerPackagedProduct>
                              <code code="61939-810-01" codeSystem="2.16.840.1.113883.6.69"/>
                              <formCode code="C43169" codeSystem="2.16.840.1.113883.3.26.1.1" displayName="BOTTLE"/>
                           </containerPackagedProduct>
                           <subjectOf>
                              <characteristic classCode="OBS">
                                 <code code="SPLCMBPRDTP" codeSystem="2.16.840.1.113883.1.11.19255"/>
                                 <value code="C112160" codeSystem="2.16.840.1.113883.3.26.1.1" displayName="Type 0: Not a Combination Product" xsi:type="CE"/>
                              </characteristic>
                           </subjectOf>
                        </asContent>
                        <asContent>
                           <quantity>
                              <numerator unit="1" value="1000"/>
                              <denominator value="1"/>
                           </quantity>
                           <containerPackagedProduct>
                              <code code="61939-810-10" codeSystem="2.16.840.1.113883.6.69"/>
                              <formCode code="C43169" codeSystem="2.16.840.1.113883.3.26.1.1" displayName="BOTTLE"/>
                           </containerPackagedProduct>
                           <subjectOf>
                              <characteristic classCode="OBS">
                                 <code code="SPLCMBPRDTP" codeSystem="2.16.840.1.113883.1.11.19255"/>
                                 <value code="C112160" codeSystem="2.16.840.1.113883.3.26.1.1" displayName="Type 0: Not a Combination Product" xsi:type="CE"/>
                              </characteristic>
                           </subjectOf>
                        </asContent>
                     </manufacturedProduct>
                     <subjectOf>
                        <approval>
                           <id extension="ANDA040190" root="2.16.840.1.113883.3.150"/>
                           <code code="C73584" codeSystem="2.16.840.1.113883.3.26.1.1" displayName="ANDA"/>
                           <author>
                              <territorialAuthority>
                                 <territory>
                                    <code code="USA" codeSystem="2.16.840.1.113883.5.28"/>
                                 </territory>
                              </territorialAuthority>
                           </author>
                        </approval>
                     </subjectOf>
                     <subjectOf>
                        <marketingAct>
                           <code code="C53292" codeSystem="2.16.840.1.113883.3.26.1.1"/>
                           <statusCode code="active"/>
                           <effectiveTime>
                              <low value="20140501"/>
                           </effectiveTime>
                        </marketingAct>
                     </subjectOf>
                     <subjectOf>
                        <policy classCode="DEADrugSchedule">
                           <code code="C48677" codeSystem="2.16.840.1.113883.3.26.1.1" displayName="CIV"/>
                        </policy>
                     </subjectOf>
                     <subjectOf>
                        <characteristic classCode="OBS">
                           <code code="SPLCOLOR" codeSystem="2.16.840.1.113883.1.11.19255"/>
                           <value code="C48325" codeSystem="2.16.840.1.113883.3.26.1.1" displayName="WHITE" xsi:type="CE">
                              <originalText>Blue Specs</originalText>
                           </value>
                        </characteristic>
                     </subjectOf>
                     <subjectOf>
                        <characteristic classCode="OBS">
                           <code code="SPLSIZE" codeSystem="2.16.840.1.113883.1.11.19255"/>
                           <value unit="mm" value="11" xsi:type="PQ"/>
                        </characteristic>
                     </subjectOf>
                     <subjectOf>
                        <characteristic classCode="OBS">
                           <code code="SPLSHAPE" codeSystem="2.16.840.1.113883.1.11.19255"/>
                           <value code="C48345" codeSystem="2.16.840.1.113883.3.26.1.1" displayName="OVAL" xsi:type="CE"/>
                        </characteristic>
                     </subjectOf>
                     <subjectOf>
                        <characteristic classCode="OBS">
                           <code code="SPLSCORE" codeSystem="2.16.840.1.113883.1.11.19255"/>
                           <value value="2" xsi:type="INT"/>
                        </characteristic>
                     </subjectOf>
                     <subjectOf>
                        <characteristic classCode="OBS">
                           <code code="SPLIMPRINT" codeSystem="2.16.840.1.113883.1.11.19255"/>
                           <value xsi:type="ST">810</value>
                        </characteristic>
                     </subjectOf>
                     <consumedIn>
                        <substanceAdministration>
                           <routeCode code="C38288" codeSystem="2.16.840.1.113883.3.26.1.1" displayName="ORAL"/>
                        </substanceAdministration>
                     </consumedIn>
                  </manufacturedProduct>
               </subject>
            </section>
         </component>
         <component>
            <section ID="i4i_indications_id_cf5bce36-4047-4d84-a9da-3268a352bd36">
               <id root="26c6ae39-74e9-414d-9dbd-e6d35f7eb79b"/>
               <code code="34067-9" codeSystem="2.16.840.1.113883.6.1" displayName="INDICATIONS &amp; USAGE SECTION"/>
               <title>1 INDICATIONS AND USAGE</title>
               <text>
                  <paragraph>Phentermine hydrochloride Tablets are  indicated as a short-term (a few weeks) adjunct in a regimen of weight reduction based on exercise, behavioral modification and caloric restriction in the management of exogenous obesity for patients with an initial body mass index ≥ 30 kg/m2, or ≥ 27 kg/m2 in the presence of other risk factors (e.g., controlled hypertension, diabetes, hyperlipidemia).</paragraph>
                  <paragraph>Below is a chart of body mass index (BMI) based on various heights and weights.</paragraph>
                  <paragraph>BMI is calculated by taking the patient’s weight, in kilograms (kg), divided by the patient’s height, in meters (m), squared. Metric conversions are as follows: pounds ÷ 2.2 = kg; inches x 0.0254 = meters.</paragraph>
                  <renderMultiMedia ID="id378" referencedObject="E145A118-77E6-41B9-98D8-6D4EB25D7952"/>
                  <paragraph>The limited usefulness of agents of this class, including phentermine, [<content styleCode="italics">see Clinical Pharmacology (<linkHtml href="http://dailymed.nlm.nih.gov/dailymed/drugInfo.cfm?id=75692">12.1</linkHtml>, <linkHtml href="http://dailymed.nlm.nih.gov/dailymed/drugInfo.cfm?id=75692">12.2</linkHtml>)</content>] should be measured against possible risk factors inherent in their use such as those described below. </paragraph>
               </text>
               <effectiveTime value="20150226"/>
               <excerpt>
                  <highlight>
                     <text>
                        <paragraph>Phentermine Hydrochloride is a sympathomimetic amine anorectic indicated as a short-term adjunct (a few weeks) in a regimen of weight reduction based on exercise, behavioral modification and caloric restriction in the management of exogenous obesity for patients with an initial body mass index ≥ 30 kg/m2, or ≥ 27 kg/m2 in the presence of other risk factors (e.g., controlled hypertension, diabetes, hyperlipidemia). (<linkHtml href="http://dailymed.nlm.nih.gov/dailymed/drugInfo.cfm?id=75692">1</linkHtml>)</paragraph>
                        <paragraph>The limited usefulness of agents of this class, including phentermine hydrochloride, should be measured against possible risk factors inherent in their use. (<linkHtml href="http://dailymed.nlm.nih.gov/dailymed/drugInfo.cfm?id=75692">1</linkHtml>) </paragraph>
                     </text>
                  </highlight>
               </excerpt>
               <component>
                  <observationMedia ID="E145A118-77E6-41B9-98D8-6D4EB25D7952">
                     <text>Body Mass Index Table</text>
                     <value mediaType="image/jpeg" xsi:type="ED">
                        <reference value="image-01.jpg"/>
                     </value>
                  </observationMedia>
               </component>
            </section>
         </component>
         <component>
            <section ID="i4i_dosage_admin_id_39524dc9-94d7-47b6-a212-ed1629036f69">
               <id root="e64d5a44-1c7d-4706-8365-2e0fe2ee6b6f"/>
               <code code="34068-7" codeSystem="2.16.840.1.113883.6.1" displayName="DOSAGE &amp; ADMINISTRATION SECTION"/>
               <title>2 DOSAGE AND ADMINISTRATION</title>
               <text>
                  <paragraph>Exogenous Obesity </paragraph>
                  <paragraph>Dosage should be individualized to obtain an adequate response with the lowest effective dose. </paragraph>
                  <paragraph>The usual adult dose is one tablet (37.5 mg) daily, as prescribed by the physician, administered before breakfast or 1 to 2 hours after breakfast. The dosage may be adjusted to the patient’s need. For some patients, half tablet (18.75 mg) daily may be adequate, while in some cases it may be desirable to give half tablets (18.75 mg) two times a day.</paragraph>
                  <paragraph>Phentermine  is not recommended for use in pediatric patients ≤ 16 years of age.</paragraph>
                  <paragraph>Late evening medication should be avoided because of the possibility of resulting insomnia. </paragraph>
               </text>
               <effectiveTime value="20150226"/>
               <excerpt>
                  <highlight>
                     <text>
                        <list listType="unordered">
                           <item>
                              <caption>•</caption>Dosage should be individualized to obtain an adequate response with the lowest effective dose. (<linkHtml href="http://dailymed.nlm.nih.gov/dailymed/drugInfo.cfm?id=75692">2</linkHtml>)</item>
                           <item>
                              <caption>•</caption>Late evening administration should be avoided (risk of insomnia). (<linkHtml href="http://dailymed.nlm.nih.gov/dailymed/drugInfo.cfm?id=75692">2</linkHtml>)</item>
                           <item>
                              <caption>•</caption>Phentermine Hydrochloride Tablets can be taken with or without food. (<linkHtml href="http://dailymed.nlm.nih.gov/dailymed/drugInfo.cfm?id=75692">12.3</linkHtml>) </item>
                        </list>
                     </text>
                  </highlight>
               </excerpt>
            </section>
         </component>
         <component>
            <section ID="i4i_dosage_form_strength_id_403d3253-9e4c-4a2e-a7ea-e5b566692b1f">
               <id root="0c76996b-95e9-4775-bb46-9eb9cfbfd737"/>
               <code code="43678-2" codeSystem="2.16.840.1.113883.6.1" displayName="DOSAGE FORMS &amp; STRENGTHS SECTION"/>
               <title>3 DOSAGE FORMS AND STRENGTHS</title>
               <text>
                  <paragraph>Tablets containing 37.5 mg phentermine hydrochloride (equivalent to 30 mg phentermine base).</paragraph>
               </text>
               <effectiveTime value="20150226"/>
               <excerpt>
                  <highlight>
                     <text>
                        <list listType="unordered">
                           <item>
                              <caption>•</caption>Tablets containing 37.5 mg phentermine hydrochloride. (<linkHtml href="http://dailymed.nlm.nih.gov/dailymed/drugInfo.cfm?id=75692">3</linkHtml>)</item>
                        </list>
                     </text>
                  </highlight>
               </excerpt>
            </section>
         </component>
         <component>
            <section ID="i4i_contraindications_id_c5d33e76-2c5c-4e74-8ee3-4eedb1f8382f">
               <id root="9aa6f8f5-f73d-4f4b-b493-b2c754b88378"/>
               <code code="34070-3" codeSystem="2.16.840.1.113883.6.1" displayName="CONTRAINDICATIONS SECTION"/>
               <title>4 CONTRAINDICATIONS</title>
               <text>
                  <list listType="unordered">
                     <item>
                        <caption>•</caption>History of cardiovascular disease (e.g., coronary artery disease, stroke, arrhythmias, congestive heart failure, uncontrolled hypertension)</item>
                     <item>
                        <caption>•</caption>During or within 14 days following the administration of monoamine oxidase inhibitors</item>
                     <item>
                        <caption>•</caption>Hyperthyroidism</item>
                     <item>
                        <caption>•</caption>Glaucoma</item>
                     <item>
                        <caption>•</caption>Agitated states</item>
                     <item>
                        <caption>•</caption>History of drug abuse</item>
                     <item>
                        <caption>•</caption>Pregnancy [<content styleCode="italics">see Use in Specific Populations (<linkHtml href="http://dailymed.nlm.nih.gov/dailymed/drugInfo.cfm?id=75692">8.1</linkHtml>)</content>]</item>
                     <item>
                        <caption>•</caption>Nursing [<content styleCode="italics">see Use in Specific Populations (<linkHtml href="http://dailymed.nlm.nih.gov/dailymed/drugInfo.cfm?id=75692">8.3</linkHtml>)</content>] </item>
                     <item>
                        <caption>•</caption>Known hypersensitivity, or idiosyncrasy to the sympathomimetic amines </item>
                  </list>
               </text>
               <effectiveTime value="20150226"/>
               <excerpt>
                  <highlight>
                     <text>
                        <list listType="unordered">
                           <item>
                              <caption>•</caption>History of cardiovascular disease (e.g., coronary artery disease, stroke, arrhythmias, congestive heart failure, uncontrolled hypertension) (<linkHtml href="http://dailymed.nlm.nih.gov/dailymed/drugInfo.cfm?id=75692">4</linkHtml>)</item>
                           <item>
                              <caption>•</caption>During or within 14 days following the administration of monoamine oxidase inhibitors (<linkHtml href="http://dailymed.nlm.nih.gov/dailymed/drugInfo.cfm?id=75692">4</linkHtml>)</item>
                           <item>
                              <caption>•</caption>Hyperthyroidism (<linkHtml href="http://dailymed.nlm.nih.gov/dailymed/drugInfo.cfm?id=75692">4</linkHtml>)</item>
                           <item>
                              <caption>•</caption>Glaucoma (<linkHtml href="http://dailymed.nlm.nih.gov/dailymed/drugInfo.cfm?id=75692">4</linkHtml>)</item>
                           <item>
                              <caption>•</caption>Agitated states (<linkHtml href="http://dailymed.nlm.nih.gov/dailymed/drugInfo.cfm?id=75692">4</linkHtml>)</item>
                           <item>
                              <caption>•</caption>History of drug abuse (<linkHtml href="http://dailymed.nlm.nih.gov/dailymed/drugInfo.cfm?id=75692">4</linkHtml>)</item>
                           <item>
                              <caption>•</caption>Pregnancy (<linkHtml href="http://dailymed.nlm.nih.gov/dailymed/drugInfo.cfm?id=75692">4</linkHtml>, <linkHtml href="http://dailymed.nlm.nih.gov/dailymed/drugInfo.cfm?id=75692">8.1</linkHtml>)</item>
                           <item>
                              <caption>•</caption>Nursing (<linkHtml href="http://dailymed.nlm.nih.gov/dailymed/drugInfo.cfm?id=75692">4</linkHtml>, <linkHtml href="http://dailymed.nlm.nih.gov/dailymed/drugInfo.cfm?id=75692">8.3</linkHtml>)</item>
                           <item>
                              <caption>•</caption>Known hypersensitivity, or idiosyncrasy to the sympathomimetic amines (<linkHtml href="http://dailymed.nlm.nih.gov/dailymed/drugInfo.cfm?id=75692">4</linkHtml>) </item>
                        </list>
                     </text>
                  </highlight>
               </excerpt>
            </section>
         </component>
         <component>
            <section ID="i4i_warnings_precautions_id_b2161db0-db2a-478e-84e9-54e635f70b0b">
               <id root="8de13a35-676a-40ab-ad59-53621aa7f8d8"/>
               <code code="43685-7" codeSystem="2.16.840.1.113883.6.1" displayName="WARNINGS AND PRECAUTIONS SECTION"/>
               <title>5 WARNINGS AND PRECAUTIONS</title>
               <effectiveTime value="20150226"/>
               <excerpt>
                  <highlight>
                     <text>
                        <table width="100%">
                           <col width="93%"/>
                           <tbody>
                              <tr styleCode="Toprule">
                                 <td>
                                    <list listType="unordered">
                                       <item>
                                          <caption>•</caption>Coadministration with other drugs for weight loss is not recommended (safety and efficacy of combination not established). (<linkHtml href="http://dailymed.nlm.nih.gov/dailymed/drugInfo.cfm?id=75692">5.1</linkHtml>)</item>
                                       <item>
                                          <caption>•</caption>Rare cases of primary pulmonary hypertension have been reported. Phentermine should be discontinued in case of new, unexplained symptoms of dyspnea, angina pectoris, syncope or lower extremity edema. (<linkHtml href="http://dailymed.nlm.nih.gov/dailymed/drugInfo.cfm?id=75692">5.2</linkHtml>) </item>
                                       <item>
                                          <caption>•</caption>Rare cases of serious regurgitant cardiac valvular disease have been reported. (<linkHtml href="http://dailymed.nlm.nih.gov/dailymed/drugInfo.cfm?id=75692">5.3</linkHtml>) </item>
                                       <item>
                                          <caption>•</caption>Tolerance to the anorectic effect usually develops within a few weeks. If this occurs, phentermine should be discontinued. The recommended dose should not be exceeded. (<linkHtml href="http://dailymed.nlm.nih.gov/dailymed/drugInfo.cfm?id=75692">5.4</linkHtml>) </item>
                                       <item>
                                          <caption>•</caption>Phentermine may impair the ability of the patient to engage in potentially hazardous activities such as operating machinery or driving a motor vehicle. (<linkHtml href="http://dailymed.nlm.nih.gov/dailymed/drugInfo.cfm?id=75692">5.5</linkHtml>) </item>
                                       <item>
                                          <caption>•</caption>Risk of abuse and dependence. The least amount feasible should be prescribed or dispensed at one time in order to minimize the possibility of overdosage. (<linkHtml href="http://dailymed.nlm.nih.gov/dailymed/drugInfo.cfm?id=75692">5.6</linkHtml>) </item>
                                       <item>
                                          <caption>•</caption>Concomitant alcohol use may result in an adverse drug reaction. (<linkHtml href="http://dailymed.nlm.nih.gov/dailymed/drugInfo.cfm?id=75692">5.7</linkHtml>)</item>
                                       <item>
                                          <caption>•</caption>Use caution in patients with even mild hypertension (risk of increase in blood pressure). (<linkHtml href="http://dailymed.nlm.nih.gov/dailymed/drugInfo.cfm?id=75692">5.8</linkHtml>)</item>
                                       <item>
                                          <caption>•</caption>A reduction in dose of insulin or oral hypoglycemic medication may be required in some patients. (<linkHtml href="http://dailymed.nlm.nih.gov/dailymed/drugInfo.cfm?id=75692">5.9</linkHtml>)</item>
                                    </list>
                                 </td>
                              </tr>
                           </tbody>
                        </table>
                     </text>
                  </highlight>
               </excerpt>
               <component>
                  <section ID="i4i_warnings_precautions_duplicate_id_739a42cf-e1a2-41a1-9610-80414c9d7a47">
                     <id root="09a78a02-ff53-48bd-b7e0-bac51f7191c1"/>
                     <code code="43685-7" codeSystem="2.16.840.1.113883.6.1" displayName="WARNINGS AND PRECAUTIONS SECTION"/>
                     <title>5.1 Coadminstration with Other Drug Products for Weight Loss</title>
                     <text>
                        <paragraph>
                           <content styleCode="bold">Phentermine Hydrochloride Tablets are  indicated only as short-term (a few weeks) monotherapy for the management of exogenous obesity. The safety and efficacy of combination therapy with phentermine and any other drug products for weight loss including prescribed drugs, over-the-counter preparations, and herbal products, or serotonergic agents such as selective serotonin reuptake inhibitors (e.g., fluoxetine, sertraline, fluvoxamine, paroxetine), have not been established. Therefore, coadministration of phentermine and these drug products is not recommended. </content>
                        </paragraph>
                     </text>
                     <effectiveTime value="20150226"/>
                  </section>
               </component>
               <component>
                  <section ID="i4i_warnings_precautions_duplicate_id_ef62201a-38ea-4611-8a41-6f568e681d4c">
                     <id root="ba820368-801b-476d-b8e7-ddda4f9482fd"/>
                     <code code="43685-7" codeSystem="2.16.840.1.113883.6.1" displayName="WARNINGS AND PRECAUTIONS SECTION"/>
                     <title>5.2 Primary Pulmonary Hypertension</title>
                     <text>
                        <paragraph>
                           <content styleCode="bold">Primary Pulmonary Hypertension (PPH) – a rare, frequently fatal disease of the lungs – has been reported to occur in patients receiving a combination of phentermine with fenfluramine or dexfenfluramine. The possibility of an association between PPH and the use of phentermine alone cannot be ruled out; there have been rare cases of PPH in patients who reportedly have taken phentermine alone.</content>The initial symptom of PPH is usually dyspnea. Other initial symptoms may include angina pectoris, syncope or lower extremity edema. Patients should be advised to report immediately any deterioration in exercise tolerance. Treatment should be discontinued in patients who develop new, unexplained symptoms of dyspnea, angina pectoris, syncope or lower extremity edema, and patients should be evaluated for the possible presence of pulmonary hypertension. </paragraph>
                     </text>
                     <effectiveTime value="20150226"/>
                  </section>
               </component>
               <component>
                  <section ID="i4i_warnings_precautions_duplicate_id_214c0d56-c246-4552-9ec3-cad44a2105b6">
                     <id root="83cbba3f-00c0-4804-8af5-d21f25929207"/>
                     <code code="43685-7" codeSystem="2.16.840.1.113883.6.1" displayName="WARNINGS AND PRECAUTIONS SECTION"/>
                     <title>5.3 Valvular Heart Disease</title>
                     <text>
                        <paragraph>
                           <content styleCode="bold">Serious regurgitant cardiac valvular disease, primarily affecting the mitral, aortic and/or tricuspid valves, has been reported in otherwise healthy persons who had taken a combination of phentermine with fenfluramine or dexfenfluramine for weight loss. The possible role of phentermine in the etiology of these valvulopathies has not been established and their course in individuals after the drugs are stopped is not known. The possibility of an association between valvular heart disease and the use of phentermine alone cannot be ruled out; there have been rare cases of valvular heart disease in patients who reportedly have taken phentermine alone. </content>
                        </paragraph>
                     </text>
                     <effectiveTime value="20150226"/>
                  </section>
               </component>
               <component>
                  <section ID="i4i_warnings_precautions_duplicate_id_2118aeca-80f7-4f31-9bf8-15557a63a969">
                     <id root="23d252f7-0426-41b5-94df-8b02671fc3fb"/>
                     <code code="43685-7" codeSystem="2.16.840.1.113883.6.1" displayName="WARNINGS AND PRECAUTIONS SECTION"/>
                     <title>5.4 Development of Tolerance, Discontinuation in Case of Tolerance</title>
                     <text>
                        <paragraph>When tolerance to the anorectant effect develops, the recommended dose should not be exceeded in an attempt to increase the effect; rather, the drug should be discontinued. </paragraph>
                     </text>
                     <effectiveTime value="20150226"/>
                  </section>
               </component>
               <component>
                  <section ID="i4i_warnings_precautions_duplicate_id_5f20ed01-ab18-42fd-8f5a-5ea9bb37d04a">
                     <id root="575b1298-1b50-4624-8958-faea22b62f30"/>
                     <code code="43685-7" codeSystem="2.16.840.1.113883.6.1" displayName="WARNINGS AND PRECAUTIONS SECTION"/>
                     <title>5.5 Effect on the Ability to Engage in Potentially Hazardous Task</title>
                     <text>
                        <paragraph>Phentermine may impair the ability of the patient to engage in potentially hazardous activities such as operating machinery or driving a motor vehicle; the patient should therefore be cautioned accordingly. </paragraph>
                     </text>
                     <effectiveTime value="20150226"/>
                  </section>
               </component>
               <component>
                  <section ID="i4i_warnings_precautions_duplicate_id_5f91e31b-f126-4155-a321-7806c25466c8">
                     <id root="cb43b125-1c36-42c4-8005-548a59060045"/>
                     <code code="43685-7" codeSystem="2.16.840.1.113883.6.1" displayName="WARNINGS AND PRECAUTIONS SECTION"/>
                     <title>5.6 Risk of Abuse and Dependence</title>
                     <text>
                        <paragraph>Phentermine is related chemically and pharmacologically to amphetamine (d- and d<content styleCode="italics">l</content>l-amphetamine) and other related stimulant drugs have been extensively abused. The possibility of abuse of phentermine should be kept in mind when evaluating the desirability of including a drug as part of a weight reduction program. See <content styleCode="italics">Drug Abuse and Dependence (<linkHtml href="http://dailymed.nlm.nih.gov/dailymed/drugInfo.cfm?id=75692">9</linkHtml>)</content> and <content styleCode="italics">Overdosage (<linkHtml href="http://dailymed.nlm.nih.gov/dailymed/drugInfo.cfm?id=75692">10</linkHtml>)</content>. </paragraph>
                        <paragraph>The least amount feasible should be prescribed or dispensed at one time in order to minimize the possibility of overdosage. </paragraph>
                     </text>
                     <effectiveTime value="20150226"/>
                  </section>
               </component>
               <component>
                  <section ID="i4i_warnings_precautions_duplicate_id_c8efa05e-3a31-4011-98e3-e474c32cfe0f">
                     <id root="cd561b36-bca3-460c-a59c-d7866b6b61b9"/>
                     <code code="43685-7" codeSystem="2.16.840.1.113883.6.1" displayName="WARNINGS AND PRECAUTIONS SECTION"/>
                     <title>5.7 Usage with Alcohol</title>
                     <text>
                        <paragraph>Concomitant use of alcohol with phentermine may result in an adverse drug reaction. </paragraph>
                     </text>
                     <effectiveTime value="20150226"/>
                  </section>
               </component>
               <component>
                  <section ID="i4i_warnings_precautions_duplicate_id_5162cf9a-3460-47a3-8122-6582b3862a03">
                     <id root="692c12ae-90a3-4888-b4c1-62f69cb24f81"/>
                     <code code="43685-7" codeSystem="2.16.840.1.113883.6.1" displayName="WARNINGS AND PRECAUTIONS SECTION"/>
                     <title>5.8 Use in Patients with Hypertension</title>
                     <text>
                        <paragraph>Use caution in prescribing phentermine for patients with even mild hypertension (risk of increase in blood pressure). </paragraph>
                     </text>
                     <effectiveTime value="20150226"/>
                  </section>
               </component>
               <component>
                  <section ID="i4i_warnings_precautions_duplicate_id_d2ab3ad0-54a0-4bd2-846b-02371e018b63">
                     <id root="4d975466-1542-47d6-b3fd-d748c06b83e6"/>
                     <code code="43685-7" codeSystem="2.16.840.1.113883.6.1" displayName="WARNINGS AND PRECAUTIONS SECTION"/>
                     <title>5.9 Use in Patients on Insulin or Oral Hypoglycemic Medications for Diabetes Mellitus</title>
                     <text>
                        <paragraph>A reduction in insulin or oral hypoglycemic medications in patients with diabetes mellitus may be required. </paragraph>
                     </text>
                     <effectiveTime value="20150226"/>
                  </section>
               </component>
            </section>
         </component>
         <component>
            <section ID="i4i_adverse_effects_id_5dc8bec4-a703-489a-bd90-231aff6af14e">
               <id root="81ef3c3d-0639-4359-aa30-61deef086e1e"/>
               <code code="34084-4" codeSystem="2.16.840.1.113883.6.1" displayName="ADVERSE REACTIONS SECTION"/>
               <title>6 ADVERSE REACTIONS</title>
               <text>
                  <paragraph>The following adverse reactions are described, or described in greater detail, in other sections: </paragraph>
                  <list listType="unordered">
                     <item>
                        <caption>•</caption>Primary pulmonary hypertension [<content styleCode="italics">see Warnings and Precautions (<linkHtml href="http://dailymed.nlm.nih.gov/dailymed/drugInfo.cfm?id=75692">5.2</linkHtml>)</content>] </item>
                     <item>
                        <caption>•</caption>Valvular heart disease [<content styleCode="italics">see Warnings and Precautions (<linkHtml href="http://dailymed.nlm.nih.gov/dailymed/drugInfo.cfm?id=75692">5.3</linkHtml>)</content>] </item>
                     <item>
                        <caption>•</caption>Effect on the ability to engage in potentially hazardous tasks [<content styleCode="italics">see Warnings and Precautions (<linkHtml href="http://dailymed.nlm.nih.gov/dailymed/drugInfo.cfm?id=75692">5.5</linkHtml>)</content>] </item>
                     <item>
                        <caption>•</caption>Withdrawal effects following prolonged high dosage administration [<content styleCode="italics">see Drug Abuse and Dependence (<linkHtml href="http://dailymed.nlm.nih.gov/dailymed/drugInfo.cfm?id=75692">9.3</linkHtml>)</content>] </item>
                  </list>
                  <paragraph>The following adverse reactions to phentermine have been identified: </paragraph>
                  <paragraph>
                     <content styleCode="underline">Cardiovascular</content>
                  </paragraph>
                  <paragraph>Primary pulmonary hypertension and/or regurgitant cardiac valvular disease, palpitation, tachycardia, elevation of blood pressure, ischemic events. </paragraph>
                  <paragraph>
                     <content styleCode="underline">Central Nervous System</content>
                  </paragraph>
                  <paragraph>Overstimulation, restlessness, dizziness, insomnia, euphoria, dysphoria, tremor, headache, psychosis.</paragraph>
                  <paragraph>
                     <content styleCode="underline">Gastrointestinal</content>
                  </paragraph>
                  <paragraph>Dryness of the mouth, unpleasant taste, diarrhea, constipation, other gastrointestinal disturbances.</paragraph>
                  <paragraph>
                     <content styleCode="underline">Allergic</content>
                  </paragraph>
                  <paragraph>Urticaria.</paragraph>
                  <paragraph>
                     <content styleCode="underline">Endocrine</content>
                  </paragraph>
                  <paragraph>Impotence, changes in libido. </paragraph>
               </text>
               <effectiveTime value="20150226"/>
               <excerpt>
                  <highlight>
                     <text>
                        <paragraph>Adverse events have been reported in the cardiovascular, central nervous, gastrointestinal, allergic, and endocrine systems. (<linkHtml href="http://dailymed.nlm.nih.gov/dailymed/drugInfo.cfm?id=75692">6</linkHtml>)</paragraph>
                        <paragraph>To report SUSPECTED ADVERSE REACTIONS, contact {enter text here} or FDA at 1-800-FDA-1088 or <linkHtml href="http://www.fda.gov/medwatch">http://www.fda.gov/medwatch</linkHtml>
                        </paragraph>
                     </text>
                  </highlight>
               </excerpt>
            </section>
         </component>
         <component>
            <section ID="i4i_interactions_id_e10966bc-2d24-419d-bff1-31fb5392e881">
               <id root="77b06a18-9d79-4d04-8c6c-39e83f6bab0d"/>
               <code code="34073-7" codeSystem="2.16.840.1.113883.6.1" displayName="DRUG INTERACTIONS SECTION"/>
               <title>7 DRUG INTERACTIONS</title>
               <effectiveTime value="20150226"/>
               <excerpt>
                  <highlight>
                     <text>
                        <list listType="unordered">
                           <item>
                              <caption>•</caption>Monoamine oxidase inhibitors: Risk of hypertensive crisis. (<linkHtml href="http://dailymed.nlm.nih.gov/dailymed/drugInfo.cfm?id=75692">4</linkHtml>, <linkHtml href="http://dailymed.nlm.nih.gov/dailymed/drugInfo.cfm?id=75692">7.1</linkHtml>)</item>
                           <item>
                              <caption>•</caption>Alcohol: Consider potential interaction (<linkHtml href="http://dailymed.nlm.nih.gov/dailymed/drugInfo.cfm?id=75692">7.2</linkHtml>)</item>
                           <item>
                              <caption>•</caption>Insulin and oral hypoglycemics: Requirements may be altered. (<linkHtml href="http://dailymed.nlm.nih.gov/dailymed/drugInfo.cfm?id=75692">7.3</linkHtml>)</item>
                           <item>
                              <caption>•</caption>Adrenergic neuron blocking drugs: Hypotensive effect may be decreased by phentermine. (<linkHtml href="http://dailymed.nlm.nih.gov/dailymed/drugInfo.cfm?id=75692">7.4</linkHtml>) </item>
                        </list>
                     </text>
                  </highlight>
               </excerpt>
               <component>
                  <section ID="i4i_drug_interaction_id_a757c93c-72a8-49ed-bd9b-4061d7b1a349">
                     <id root="afd2fc80-ee06-4498-9c89-a5b09c8cf8f8"/>
                     <code code="34073-7" codeSystem="2.16.840.1.113883.6.1" displayName="DRUG INTERACTIONS SECTION"/>
                     <title>7.1 Monoamine Oxidase Inhibitors</title>
                     <text>
                        <paragraph>Use of phentermine is contraindicated during or within 14 days following the administration of monoamine oxidase inhibitors because of the risk of hypertensive crisis. </paragraph>
                     </text>
                     <effectiveTime value="20150226"/>
                  </section>
               </component>
               <component>
                  <section ID="i4i_drug_interaction_id_5d546735-e03e-453e-85be-79cc8c6fec7b">
                     <id root="1ee5d976-56a2-4278-a886-7c71eee98957"/>
                     <code code="34073-7" codeSystem="2.16.840.1.113883.6.1" displayName="DRUG INTERACTIONS SECTION"/>
                     <title>7.2 Alcohol</title>
                     <text>
                        <paragraph>Concomitant use of alcohol with phentermine may result in an adverse drug reaction. </paragraph>
                     </text>
                     <effectiveTime value="20150226"/>
                  </section>
               </component>
               <component>
                  <section ID="i4i_drug_interaction_id_51cebf9c-0e96-4bd9-97ba-a67b6e6537c5">
                     <id root="e401616d-97fa-41fe-a049-fd869580d6b0"/>
                     <code code="34073-7" codeSystem="2.16.840.1.113883.6.1" displayName="DRUG INTERACTIONS SECTION"/>
                     <title>7.3 Insulin and Oral Hypoglycemic Medications</title>
                     <text>
                        <paragraph>Requirements may be altered [<content styleCode="italics">see Warnings and Precautions (<linkHtml href="http://dailymed.nlm.nih.gov/dailymed/drugInfo.cfm?id=75692">5.9</linkHtml>)</content>]. </paragraph>
                     </text>
                     <effectiveTime value="20150226"/>
                  </section>
               </component>
               <component>
                  <section ID="i4i_drug_interaction_id_e56a486a-72a9-4691-a754-562c632b9c91">
                     <id root="15518f15-ae7b-495e-b002-24d203d7950e"/>
                     <code code="34073-7" codeSystem="2.16.840.1.113883.6.1" displayName="DRUG INTERACTIONS SECTION"/>
                     <title>7.4 Adrenergic Neuron Blocking Drug</title>
                     <text>
                        <paragraph>Phentermine may decrease the hypotensive effect of adrenergic neuron blocking drugs.</paragraph>
                     </text>
                     <effectiveTime value="20150226"/>
                  </section>
               </component>
            </section>
         </component>
         <component>
            <section ID="i4i_specific_populations_id_bd7f9ca4-6375-404b-ade9-4ded650aae49">
               <id root="edd1db9b-dfeb-447f-ab95-4bb460ced801"/>
               <code code="43684-0" codeSystem="2.16.840.1.113883.6.1" displayName="USE IN SPECIFIC POPULATIONS SECTION"/>
               <title>8 USE IN SPECIFIC POPULATIONS</title>
               <effectiveTime value="20150226"/>
               <excerpt>
                  <highlight>
                     <text>
                        <list listType="unordered">
                           <item>
                              <caption>•</caption>Nursing mothers: Discontinue drug or nursing taking into consideration importance of drug to mother. (<linkHtml href="http://dailymed.nlm.nih.gov/dailymed/drugInfo.cfm?id=75692">4</linkHtml>, <linkHtml href="http://dailymed.nlm.nih.gov/dailymed/drugInfo.cfm?id=75692">8.3</linkHtml>)</item>
                           <item>
                              <caption>•</caption>Pediatric use: Safety and effectiveness not established. (<linkHtml href="http://dailymed.nlm.nih.gov/dailymed/drugInfo.cfm?id=75692">8.4</linkHtml>)</item>
                           <item>
                              <caption>•</caption>Geriatric use: Due to substantial renal excretion, use with caution. (<linkHtml href="http://dailymed.nlm.nih.gov/dailymed/drugInfo.cfm?id=75692">8.5</linkHtml>)</item>
                           <item>
                              <caption>•</caption>Use caution when administering phentermine to patients with renal impairment (<linkHtml href="http://dailymed.nlm.nih.gov/dailymed/drugInfo.cfm?id=75692">8.6</linkHtml>) </item>
                        </list>
                     </text>
                  </highlight>
               </excerpt>
               <component>
                  <section ID="i4i_pregnancy_id_b37137b4-1637-4bc6-a06f-c774bbb4ba9f">
                     <id root="29e0d6d9-1d11-46e9-bff1-be9bda6215b1"/>
                     <code code="42228-7" codeSystem="2.16.840.1.113883.6.1" displayName="PREGNANCY SECTION"/>
                     <title>8.1 Pregnancy</title>
                     <text>
                        <paragraph>Teratogenic Effects </paragraph>
                        <paragraph>Pregnancy category X</paragraph>
                        <paragraph>Phentermine is contraindicated during pregnancy because weight loss offers no potential benefit to a pregnant woman and may result in fetal harm. A minimum weight gain, and no weight loss, is currently recommended for all pregnant women, including those who are already overweight or obese, due to obligatory weight gain that occurs in maternal tissues during pregnancy. Phentermine has pharmacologic activity similar to amphetamine (d- and d<content styleCode="italics">l</content>l-amphetamine) [<content styleCode="italics">see Clinical Pharmacology (<linkHtml href="http://dailymed.nlm.nih.gov/dailymed/drugInfo.cfm?id=75692">12.1</linkHtml>)</content>]. Animal reproduction studies have not been conducted with phentermine. If this drug is used during pregnancy, or if the patient becomes pregnant while taking this drug, the patient should be apprised of the potential hazard to a fetus. </paragraph>
                     </text>
                     <effectiveTime value="20150226"/>
                  </section>
               </component>
               <component>
                  <section ID="i4i_nursing_mothers_id_8bae5015-92ed-4a9c-9ba1-143db6d97bcb">
                     <id root="2c127477-873d-4a9b-a846-68090775b9a0"/>
                     <code code="34080-2" codeSystem="2.16.840.1.113883.6.1" displayName="NURSING MOTHERS SECTION"/>
                     <title>8.3 Nursing Mothers</title>
                     <text>
                        <paragraph>It is not known if phentermine is excreted in human milk; however, other amphetamines are present in human milk. Because of the potential for serious adverse reactions in nursing infants, a decision should be made whether to discontinue nursing or to discontinue the drug, taking into account the importance of the drug to the mother. </paragraph>
                     </text>
                     <effectiveTime value="20150226"/>
                  </section>
               </component>
               <component>
                  <section ID="i4i_pediatric_use_id_7340bb75-191b-4ca8-ab78-114f19eeda73">
                     <id root="87f0b96a-a327-4946-9e8a-e678c2a3598b"/>
                     <code code="34081-0" codeSystem="2.16.840.1.113883.6.1" displayName="PEDIATRIC USE SECTION"/>
                     <title>8.4 Pediatric Use</title>
                     <text>
                        <paragraph>Safety and effectiveness in pediatric patients have not been established. Because pediatric obesity is a chronic condition requiring long-term treatment, the use of this product, approved for short-term therapy, is not recommended. </paragraph>
                     </text>
                     <effectiveTime value="20150226"/>
                  </section>
               </component>
               <component>
                  <section ID="i4i_geriatric_use_id_0946e0c1-5f12-4cf6-a90f-741723041c2b">
                     <id root="a3b45d8c-09f6-4710-ac73-19782d80d3d2"/>
                     <code code="34082-8" codeSystem="2.16.840.1.113883.6.1" displayName="GERIATRIC USE SECTION"/>
                     <title>8.5 Geriatric Use</title>
                     <text>
                        <paragraph>In general, dose selection for an elderly patient should be cautious, usually starting at the low end of the dosing range, reflecting the greater frequency of decreased hepatic, renal, or cardiac function, and of concomitant disease or other drug therapy. </paragraph>
                        <paragraph>This drug is known to be substantially excreted by the kidney, and the risk of toxic reactions to this drug may be greater in patients with impaired renal function. Because elderly patients are more likely to have decreased renal function, care should be taken in dose selection, and it may be useful to monitor renal function. </paragraph>
                     </text>
                     <effectiveTime value="20150226"/>
                  </section>
               </component>
               <component>
                  <section ID="i4i_specific_populations_duplicate_id_b862d0aa-da87-4037-acf0-8a29212e3620">
                     <id root="2d7ddb50-93e1-4048-b9ad-f880b799422f"/>
                     <code code="43684-0" codeSystem="2.16.840.1.113883.6.1" displayName="USE IN SPECIFIC POPULATIONS SECTION"/>
                     <title>8.6 Renal Impairment</title>
                     <text>
                        <paragraph>Phentermine was not studied in patients with renal impairment. Based on the reported excretion of phentermine in urine, exposure increases can be expected in patients with renal impairment. Use caution when administering phentermine to patients with renal impairment [<content styleCode="italics">see Clinical Pharmacology (<linkHtml href="http://dailymed.nlm.nih.gov/dailymed/drugInfo.cfm?id=75692">12.3</linkHtml>)</content>]. </paragraph>
                     </text>
                     <effectiveTime value="20150226"/>
                  </section>
               </component>
            </section>
         </component>
         <component>
            <section ID="i4i_abuse_dependence_id_eae26843-f19c-4b48-ae41-6dcd3f1b88bc">
               <id root="ba0a9c49-e08b-4b36-9970-48561e10f898"/>
               <code code="42227-9" codeSystem="2.16.840.1.113883.6.1" displayName="DRUG ABUSE AND DEPENDENCE SECTION"/>
               <title>9 DRUG ABUSE AND DEPENDENCE</title>
               <effectiveTime value="20150226"/>
               <component>
                  <section ID="i4i_controlled_substance_id_64066967-a5dd-48dc-975d-33f35f2fab12">
                     <id root="128afbf6-6d36-494d-85d6-155807239da1"/>
                     <code code="34085-1" codeSystem="2.16.840.1.113883.6.1" displayName="CONTROLLED SUBSTANCE SECTION"/>
                     <title>9.1 Controlled Substance</title>
                     <text>
                        <paragraph>Phentermine is a Schedule IV controlled substance. </paragraph>
                     </text>
                     <effectiveTime value="20150226"/>
                  </section>
               </component>
               <component>
                  <section ID="i4i_abuse_id_7197da3b-ad2c-4561-93d0-ff540fbf2b4c">
                     <id root="c5139a84-001f-4945-af6b-f10ac86ec155"/>
                     <code code="34086-9" codeSystem="2.16.840.1.113883.6.1" displayName="ABUSE SECTION"/>
                     <title>9.2 Abuse</title>
                     <text>
                        <paragraph>Phentermine is related chemically and pharmacologically to the amphetamines. Amphetamines and other stimulant drugs have been extensively abused and the possibility of abuse of phentermine should be kept in mind when evaluating the desirability of including a drug as part of a weight reduction program. </paragraph>
                     </text>
                     <effectiveTime value="20150226"/>
                  </section>
               </component>
               <component>
                  <section ID="i4i_dependence_id_9eac2bb2-b766-466e-a0f5-b2668bab04c2">
                     <id root="10252879-0c51-4a2c-a63c-66a43ec789f9"/>
                     <code code="34087-7" codeSystem="2.16.840.1.113883.6.1" displayName="DEPENDENCE SECTION"/>
                     <title>9.3 Dependence</title>
                     <text>
                        <paragraph>Abuse of amphetamines and related drugs may be associated with intense psychological dependence and severe social dysfunction. There are reports of patients who have increased the dosage of these drugs to many times than recommended. Abrupt cessation following prolonged high dosage administration results in extreme fatigue and mental depression; changes are also noted on the sleep EEG. Manifestations of chronic intoxication with anorectic drugs include severe dermatoses, marked insomnia, irritability, hyperactivity and personality changes. A severe manifestation of chronic intoxication is psychosis, often clinically indistinguishable from schizophrenia. </paragraph>
                     </text>
                     <effectiveTime value="20150226"/>
                  </section>
               </component>
            </section>
         </component>
         <component>
            <section ID="i4i_overdosage_id_73ae3677-82b6-482a-ba80-4a3309a4f30e">
               <id root="fbeac9fc-7dcd-4ea6-b091-facef61d590a"/>
               <code code="34088-5" codeSystem="2.16.840.1.113883.6.1" displayName="OVERDOSAGE SECTION"/>
               <title>10 OVERDOSAGE</title>
               <text>
                  <paragraph>The least amount feasible should be prescribed or dispensed at one time in order to minimize the possibility of overdosage. </paragraph>
               </text>
               <effectiveTime value="20150226"/>
               <component>
                  <section ID="i4i_overdosage_duplicate_id_17a81c72-d32e-4fe5-ab49-8c4891cc9ff4">
                     <id root="130d77e2-af2d-47c2-b3dd-c451f64b71e4"/>
                     <code code="34088-5" codeSystem="2.16.840.1.113883.6.1" displayName="OVERDOSAGE SECTION"/>
                     <title>10.1 Acute Overdosage</title>
                     <text>
                        <paragraph>Manifestations of acute overdosage include restlessness, tremor, hyperreflexia, rapid respiration, confusion, assaultiveness, hallucinations, and panic states. Fatigue and depression usually follow the central stimulation. Cardiovascular effects include arrhythmia, hypertension or hypotension, and circulatory collapse. Gastrointestinal symptoms include nausea, vomiting, diarrhea and abdominal cramps. Overdosage of pharmacologically similar compounds has resulted in fatal poisoning usually terminates in convulsions and coma. Management of acute phentermine hydrochloride intoxication is largely symptomatic and includes lavage and sedation with a barbiturate. Experience with hemodialysis or peritoneal dialysis is inadequate to permit recommendations in this regard. Acidification of the urine increases phentermine excretion. Intravenous phentolamine (Regitine®, CIBA) has been suggested on pharmacologic grounds for<content styleCode="bold"> possible acute, severe hypertension, if this complicates overdosage. </content>
                        </paragraph>
                     </text>
                     <effectiveTime value="20150226"/>
                  </section>
               </component>
               <component>
                  <section ID="i4i_overdosage_duplicate_id_6975f365-9cee-4e2f-b371-a7fced3500b8">
                     <id root="1d96b076-5c1e-47ee-9759-2881eec9c0bd"/>
                     <code code="34088-5" codeSystem="2.16.840.1.113883.6.1" displayName="OVERDOSAGE SECTION"/>
                     <title>10.2 Chronic Intoxication</title>
                     <text>
                        <paragraph>Manifestations of chronic intoxication with anorectic drugs include severe dermatoses, marked insomnia, irritability, hyperactivity and personality changes. The most severe manifestation of chronic intoxications is psychosis, often clinically indistinguishable from schizophrenia. See <content styleCode="italics">Drug Abuse and Dependence (<linkHtml href="http://dailymed.nlm.nih.gov/dailymed/drugInfo.cfm?id=75692">9.3</linkHtml>)</content>. </paragraph>
                     </text>
                     <effectiveTime value="20150226"/>
                  </section>
               </component>
            </section>
         </component>
         <component>
            <section ID="i4i_description_id_2a544fae-30dc-4355-8d34-05e208566834">
               <id root="3ba6fcbf-2e32-47c8-adc5-19470bc7ec47"/>
               <code code="34089-3" codeSystem="2.16.840.1.113883.6.1" displayName="DESCRIPTION SECTION"/>
               <title>11 DESCRIPTION</title>
               <text>
                  <paragraph>Phentermine hydrochloride USP is a sympathomimetic amine anorectic. It has the chemical name of α,α,-Dimethylphenethylamine hydrochloride. The structural formula is as follows:</paragraph>
                  <renderMultiMedia ID="id638" referencedObject="C3C19F31-AB9B-43EF-91C1-32D6E1D23D93"/>
                  <paragraph>C10H15N•HCl M.W. 185.7</paragraph>
                  <paragraph>Phentermine hydrochloride is a white, odorless, hygroscopic, crystalline powder which is soluble in water and lower alcohols, slightly soluble in chloroform and insoluble in ether.</paragraph>
                  <paragraph>Phentermine hydrochloride, an anorectic agent for oral administration, is available as a tablet containing 37.5 mg of phentermine hydrochloride (equivalent to 30 mg of phentermine base).</paragraph>
                  <paragraph>Each tablet contains the following inactive ingredients: starch, lactose anhydrous, microcrystalline cellulose, colloidal silicon dioxide, stearic acid, magnesium stearate and blue sugar spheres.  </paragraph>
               </text>
               <effectiveTime value="20150226"/>
               <component>
                  <observationMedia ID="C3C19F31-AB9B-43EF-91C1-32D6E1D23D93">
                     <text>Molecular Structure</text>
                     <value mediaType="image/jpeg" xsi:type="ED">
                        <reference value="image-02.jpg"/>
                     </value>
                  </observationMedia>
               </component>
            </section>
         </component>
         <component>
            <section ID="i4i_clinical_pharmacology_id_6222453d-8356-4105-b0dd-42d0c2db9aee">
               <id root="23796c48-4af9-446a-83e1-803f9cdca97b"/>
               <code code="34090-1" codeSystem="2.16.840.1.113883.6.1" displayName="CLINICAL PHARMACOLOGY SECTION"/>
               <title>12 CLINICAL PHARMACOLOGY</title>
               <effectiveTime value="20150226"/>
               <component>
                  <section ID="i4i_mechanism_action_id_d29ca8f6-70a7-4f86-a207-daea34d523c7">
                     <id root="faa1f5b8-2861-4bca-aecf-30c890e340a7"/>
                     <code code="43679-0" codeSystem="2.16.840.1.113883.6.1" displayName="MECHANISM OF ACTION SECTION"/>
                     <title>12.1 Mechanism of Action</title>
                     <text>
                        <paragraph>Phentermine is a sympathomimetic amine with pharmacologic activity similar to the prototype drugs of this class used in obesity, amphetamine (d- and d<content styleCode="italics">l</content>l-amphetamine). Drugs of this class used in obesity are commonly known as “anorectics” or “anorexigenics.” It has not been established that the primary action of such drugs in treating obesity is one of appetite suppression since other central nervous system actions, or metabolic effects, may also be involved. </paragraph>
                     </text>
                     <effectiveTime value="20150226"/>
                  </section>
               </component>
               <component>
                  <section ID="i4i_pharmacodynamics_id_19f0aeb9-ca8f-4019-9cfc-19c71f703a33">
                     <id root="7920ee55-9208-45d6-b36c-d89276f3372d"/>
                     <code code="43681-6" codeSystem="2.16.840.1.113883.6.1" displayName="PHARMACODYNAMICS SECTION"/>
                     <title>12.2 Pharmacodynamics</title>
                     <text>
                        <paragraph>Typical of amphetamines include central nervous system stimulation and elevation of blood pressure. Tachyphylaxis and tolerance have been demonstrated with all drugs of this class in which these phenomena have been looked for. </paragraph>
                     </text>
                     <effectiveTime value="20150226"/>
                  </section>
               </component>
               <component>
                  <section ID="i4i_pharmacokinetics_id_96f107f3-aa8b-48d5-81bc-9f686d058f64">
                     <id root="9920d66a-bf58-4bcc-acfa-28ad32542fec"/>
                     <code code="43682-4" codeSystem="2.16.840.1.113883.6.1" displayName="PHARMACOKINETICS SECTION"/>
                     <title>12.3 Pharmacokinetics</title>
                     <text>
                        <paragraph>Following the administration of phentermine, phentermine reaches peak concentrations (Cmax) after 3 to 4.4 hours. </paragraph>
                        <paragraph>
                           <content styleCode="underline">Specific Populations</content>
                        </paragraph>
                        <paragraph>
                           <content styleCode="italics">Renal Impairment </content>
                        </paragraph>
                        <paragraph>Phentermine was not studied in patients with renal impairment. The literature reported cumulative urinary excretion of phentermine under uncontrolled urinary pH conditions is 62% to 85%. Exposure increases can be expected in patients with renal impairment. Use caution when administering phentermine to patients with renal impairment. </paragraph>
                        <paragraph>
                           <content styleCode="underline">Drug Interactions</content>
                        </paragraph>
                        <paragraph>In a single-dose study comparing the exposures after oral administration of a combination capsule of 15 mg phentermine and 92 mg topiramate to the exposures after oral administration of a 15 mg phentermine capsule or a 92 mg topiramate capsule, there is no significant topiramate exposure change in the presence of phentermine.  However in the presence of topiramate, phentermine C<sub>max</sub> and AUC increase 13% and 42 % respectively.  </paragraph>
                     </text>
                     <effectiveTime value="20150226"/>
                  </section>
               </component>
            </section>
         </component>
         <component>
            <section ID="i4i_nonclinical_toxicology_id_d29d5aac-73ed-4d71-9e1f-60e4b034a508">
               <id root="a01ff37b-affc-4136-a843-75cd1ee0ef92"/>
               <code code="43680-8" codeSystem="2.16.840.1.113883.6.1" displayName="NONCLINICAL TOXICOLOGY SECTION"/>
               <title>13 NONCLINICAL TOXICOLOGY</title>
               <effectiveTime value="20150226"/>
               <component>
                  <section ID="i4i_carcinogenesis_mutagenesis_fertility_id_44586273-7933-44ed-a0cd-7b9d1f9b021d">
                     <id root="e15e3a49-ea82-416a-99f4-40c80338364f"/>
                     <code code="34083-6" codeSystem="2.16.840.1.113883.6.1" displayName="CARCINOGENESIS &amp; MUTAGENESIS &amp; IMPAIRMENT OF FERTILITY SECTION"/>
                     <title>13.1 Carcinogenesis, Mutagenesis, Impairment of Fertility</title>
                     <text>
                        <paragraph>Studies have not been performed with phentermine to determine the potential for carcinogenesis, mutagenesis or impairment of fertility. </paragraph>
                     </text>
                     <effectiveTime value="20150226"/>
                  </section>
               </component>
            </section>
         </component>
         <component>
            <section ID="i4i_clinical_studies_id_6e65c604-0296-45f8-9112-4fa3310681db">
               <id root="e544531a-36c9-4c78-9e82-c55f4bc57595"/>
               <code code="34092-7" codeSystem="2.16.840.1.113883.6.1" displayName="CLINICAL STUDIES SECTION"/>
               <title>14 CLINICAL STUDIES</title>
               <text>
                  <paragraph>In relatively short-term clinical trials, adult obese subjects instructed in dietary management and treated with “anorectic” drugs lost more weight on the average than those treated with placebo and diet. </paragraph>
                  <paragraph>The magnitude of increased weight loss of drug-treated patients over placebo-treated patients is only a fraction of a pound a week. The rate of weight loss is greatest in the first weeks of therapy for both drug and placebo subjects and tends to decrease in succeeding weeks. The possible origins of the increased weight loss due to the various drug effects are not established. The amount of weight loss associated with the use of an “anorectic” drug varies from trial to trial, and the increased weight loss appears to be related in part to variables other than the drugs prescribed, such as the physician-investigator, the population treated and the diet prescribed. Studies do not permit conclusions as to the relative importance of the drug and non-drug factors on weight loss. </paragraph>
                  <paragraph>The natural history of obesity is measured over several years, whereas the studies cited are restricted to a few weeks’ duration; thus, the total impact of drug-induced weight loss over that of diet alone must be considered clinically limited. </paragraph>
               </text>
               <effectiveTime value="20150226"/>
            </section>
         </component>
         <component>
            <section ID="i4i_how_supplied_id_c7e97fbb-aef0-4486-9561-663cc16af1f3">
               <id root="17281042-a120-48e7-81ef-f6a5a1ca69bb"/>
               <code code="34069-5" codeSystem="2.16.840.1.113883.6.1" displayName="HOW SUPPLIED SECTION"/>
               <title>16 HOW SUPPLIED/STORAGE AND HANDLING</title>
               <text>
                  <paragraph>16 HOW SUPPLIED/STORAGE AND HANDLING</paragraph>
                  <paragraph>Phentermine Hydrochloride Tablets, USP 37.5 mg are white oval shaped bisected tablet with blue specs debossed with 810 on bisected side.    </paragraph>
                  <paragraph>Tablets are packaged in bottles of 100 (NDC 61939-810-01); and 1000 (NDC 61939-810-10).</paragraph>
                  <paragraph>Store at 20° to 25°C (68° to 77°F) [See USP Controlled Room Temperature].</paragraph>
                  <paragraph>Dispense in a tight container as defined in the USP, with a child-resistant closure (as required).</paragraph>
                  <paragraph>Keep out of the reach of children.</paragraph>
               </text>
               <effectiveTime value="20150226"/>
            </section>
         </component>
         <component>
            <section ID="i4i_info_patients_id_a50193ea-3456-4d53-b3a4-39a20ac0910c">
               <id root="6f08a496-a6a3-416f-8332-5facae5c4f54"/>
               <code code="34076-0" codeSystem="2.16.840.1.113883.6.1" displayName="INFORMATION FOR PATIENTS SECTION"/>
               <title>17 PATIENT COUNSELING INFORMATION</title>
               <text>
                  <paragraph>Patients must be informed that phentermine hydrochloride is a <content styleCode="italics">short-term</content> (a few weeks) adjunct in a regimen of weight reduction based on exercise, behavioral modification and caloric restriction in the management of exogenous obesity, and that coadministration of phentermine with other drugs for weight loss is not recommended [<content styleCode="italics">see Indications and Usage (<linkHtml href="http://dailymed.nlm.nih.gov/dailymed/drugInfo.cfm?id=75692">1</linkHtml>) and Warnings and Precautions (<linkHtml href="http://dailymed.nlm.nih.gov/dailymed/drugInfo.cfm?id=75692">5.1</linkHtml>)</content>]. </paragraph>
                  <paragraph>Patients must be instructed on how much phentermine to take, and when and how to take it [<content styleCode="italics">see Dosage and Administration (<linkHtml href="http://dailymed.nlm.nih.gov/dailymed/drugInfo.cfm?id=75692">3</linkHtml>)</content>]. </paragraph>
                  <paragraph>Advise pregnant women and nursing mothers not to use phentermine [<content styleCode="italics">see Use in Specific Populations (<linkHtml href="http://dailymed.nlm.nih.gov/dailymed/drugInfo.cfm?id=75692">8.1</linkHtml>, <linkHtml href="http://dailymed.nlm.nih.gov/dailymed/drugInfo.cfm?id=75692">8.3</linkHtml>)</content>]. </paragraph>
                  <paragraph>Patients must be informed about the risks of use of phentermine (including the risks discussed in Warnings and Precautions), about the symptoms of potential adverse reactions and when to contact a physician and/or take other action. The risks include, but are not limited to: </paragraph>
                  <list listType="unordered">
                     <item>
                        <caption>•</caption>Development of primary pulmonary hypertension [<content styleCode="italics">see Warnings and Precautions (<linkHtml href="http://dailymed.nlm.nih.gov/dailymed/drugInfo.cfm?id=75692">5.2</linkHtml>)</content>] </item>
                     <item>
                        <caption>•</caption>Development of serious valvular heart disease [<content styleCode="italics">see Warnings and Precautions (<linkHtml href="http://dailymed.nlm.nih.gov/dailymed/drugInfo.cfm?id=75692">5.3</linkHtml>)</content>] </item>
                     <item>
                        <caption>•</caption>Effects on the ability to engage in potentially hazardous tasks [<content styleCode="italics">see Warnings and Precautions (<linkHtml href="http://dailymed.nlm.nih.gov/dailymed/drugInfo.cfm?id=75692">5.5</linkHtml>)</content>] </item>
                     <item>
                        <caption>•</caption>The risk of an increase in blood pressure [<content styleCode="italics">see Warnings and Precautions (<linkHtml href="http://dailymed.nlm.nih.gov/dailymed/drugInfo.cfm?id=75692">5.8</linkHtml>) and Adverse Reactions (<linkHtml href="http://dailymed.nlm.nih.gov/dailymed/drugInfo.cfm?id=75692">6</linkHtml>)</content>] </item>
                     <item>
                        <caption>•</caption>The risk of interactions [<content styleCode="italics">see Contraindications (<linkHtml href="http://dailymed.nlm.nih.gov/dailymed/drugInfo.cfm?id=75692">4</linkHtml>), Warnings and Precautions (<linkHtml href="http://dailymed.nlm.nih.gov/dailymed/drugInfo.cfm?id=75692">5.7</linkHtml>, <linkHtml href="http://dailymed.nlm.nih.gov/dailymed/drugInfo.cfm?id=75692">5.9</linkHtml>) and Drug Interactions (<linkHtml href="http://dailymed.nlm.nih.gov/dailymed/drugInfo.cfm?id=75692">7</linkHtml>)</content>] </item>
                  </list>
                  <paragraph>See also, for example, <content styleCode="italics">Adverse Reactions (<linkHtml href="http://dailymed.nlm.nih.gov/dailymed/drugInfo.cfm?id=75692">6</linkHtml>)</content> and <content styleCode="italics">Use in Specific Populations (<linkHtml href="http://dailymed.nlm.nih.gov/dailymed/drugInfo.cfm?id=75692">8</linkHtml>)</content>. </paragraph>
                  <paragraph>The patients must also be informed about </paragraph>
                  <list listType="unordered">
                     <item>
                        <caption>•</caption>the potential for developing tolerance and actions if they suspect development of tolerance [<content styleCode="italics">see Warnings and Precautions (<linkHtml href="http://dailymed.nlm.nih.gov/dailymed/drugInfo.cfm?id=75692">5.4</linkHtml>)</content>] and </item>
                     <item>
                        <caption>•</caption>the risk of dependence and the potential consequences of abuse [<content styleCode="italics">see Warnings and Precautions (<linkHtml href="http://dailymed.nlm.nih.gov/dailymed/drugInfo.cfm?id=75692">5.6</linkHtml>), Drug Abuse and Dependence (<linkHtml href="http://dailymed.nlm.nih.gov/dailymed/drugInfo.cfm?id=75692">9</linkHtml>), and Overdosage (<linkHtml href="http://dailymed.nlm.nih.gov/dailymed/drugInfo.cfm?id=75692">10</linkHtml>)</content>]. </item>
                  </list>
                  <paragraph>Tell patients to keep phentermine in a safe place to prevent theft, accidental overdose, misuse or abuse. Selling or giving away phentermine may harm others and is against the law.</paragraph>
                  <paragraph>All trademarks are the property of their respective owners.</paragraph>
                  <paragraph>Manufactured for Mikah Pharma LLC by:</paragraph>
                  <paragraph>Elite Laboratories, Inc.</paragraph>
                  <paragraph>Northvale, NJ 07647</paragraph>
                  <paragraph>Issued 01/2014</paragraph>
               </text>
               <effectiveTime value="20150226"/>
            </section>
         </component>
         <component>
            <section ID="i4i_Principal_display_panel_id_0245c572-861e-417b-baad-0de642cc5bef">
               <id root="106d6900-56eb-426d-a278-26c8d54d3eb9"/>
               <code code="51945-4" codeSystem="2.16.840.1.113883.6.1" displayName="PACKAGE LABEL.PRINCIPAL DISPLAY PANEL"/>
               <title>PACKAGE/LABEL PRINCIPAL DISPLAY PANEL – 37.5 mg</title>
               <text>
                  <renderMultiMedia ID="id745" referencedObject="ID_64642aa9-41e6-4751-9d3d-5b07a3248c11">
                     <caption>Phentermine Hydrochloride Tablets, USP 37.5 mg - 1000 count </caption>
                  </renderMultiMedia>
               </text>
               <effectiveTime value="20150226"/>
               <component>
                  <observationMedia ID="ID_64642aa9-41e6-4751-9d3d-5b07a3248c11">
                     <text>Phentermine Hydrochloride Tablets, USP 37.5 mg - 1000 count</text>
                     <value mediaType="image/jpeg" xsi:type="ED">
                        <reference value="image-03.jpg"/>
                     </value>
                  </observationMedia>
               </component>
            </section>
         </component>
      </structuredBody>
   </component>
</document>